.gitignore
LICENSE.txt
MANIFEST.in
README.md
README.txt
setup.py
spinapi/__init__.py
spinapi/__version__.py
spinapi/libspinapi.so
spinapi/libspinapi64.so
spinapi/spinapi.py
spinapi.egg-info/PKG-INFO
spinapi.egg-info/SOURCES.txt
spinapi.egg-info/dependency_links.txt
spinapi.egg-info/top_level.txt