Metadata-Version: 1.0
Name: spinapi
Version: 3.2.2
Summary: Python wrapper around the Spincore PulseBlaster API using ctypes.
Home-page: https://bitbucket.org/cbillington/spinapi/
Author: Chris Billington
Author-email: chrisjbillington@gmail.com
License: BSD
Platform: UNKNOWN
